django_forms_workflows/__init__.py
django_forms_workflows/admin.py
django_forms_workflows/apps.py
django_forms_workflows/data_sources/__init__.py
django_forms_workflows/data_sources/base.py
django_forms_workflows/data_sources/database_source.py
django_forms_workflows/data_sources/ldap_source.py
django_forms_workflows/data_sources/user_source.py
django_forms_workflows/email_backends/__init__.py
django_forms_workflows/email_backends/gmail_api.py
django_forms_workflows/form_builder_urls.py
django_forms_workflows/form_builder_views.py
django_forms_workflows/forms.py
django_forms_workflows/handlers/__init__.py
django_forms_workflows/handlers/api_handler.py
django_forms_workflows/handlers/base.py
django_forms_workflows/handlers/database_handler.py
django_forms_workflows/handlers/email_handler.py
django_forms_workflows/handlers/executor.py
django_forms_workflows/handlers/file_handler.py
django_forms_workflows/handlers/ldap_handler.py
django_forms_workflows/ldap_backend.py
django_forms_workflows/management/commands/create_default_templates.py
django_forms_workflows/management/commands/seed_farm_demo.py
django_forms_workflows/management/commands/seed_prefill_sources.py
django_forms_workflows/management/commands/sync_ldap_profiles.py
django_forms_workflows/management/commands/test_db_connection.py
django_forms_workflows/migrations/0001_initial.py
django_forms_workflows/migrations/0002_prefillsource_alter_formfield_prefill_source_and_more.py
django_forms_workflows/migrations/0003_postsubmissionaction.py
django_forms_workflows/migrations/0004_formtemplate.py
django_forms_workflows/migrations/0005_advanced_conditional_logic.py
django_forms_workflows/migrations/0006_workflowdefinition_visual_workflow_data_and_more.py
django_forms_workflows/migrations/0007_add_userprofile_ldap_enhancements.py
django_forms_workflows/migrations/0008_add_file_workflow_models.py
django_forms_workflows/migrations/0009_add_formfield_readonly.py
django_forms_workflows-0.7.7.dist-info/METADATA
django_forms_workflows-0.7.7.dist-info/WHEEL
django_forms_workflows-0.7.7.dist-info/licenses/LICENSE
django_forms_workflows-0.7.7.dist-info/RECORD
