Metadata-Version: 2.4
Name: django-forms-workflows
Version: 0.7.7
Summary: Enterprise-grade, database-driven form builder with approval workflows and external data integration
License: LGPL-3.0-only
License-File: LICENSE
Keywords: django,forms,workflows,approval,form-builder,dynamic-forms,ldap,enterprise,audit,database-driven,sso,saml,oauth2
Author: Matt Davis
Author-email: matt@opensensor.io
Requires-Python: >=3.10,<4.0
Classifier: License :: OSI Approved :: GNU Lesser General Public License v3 (LGPLv3)
Classifier: Programming Language :: Python :: 3
Classifier: Programming Language :: Python :: 3.10
Classifier: Programming Language :: Python :: 3.11
Classifier: Programming Language :: Python :: 3.12
Classifier: Programming Language :: Python :: 3.13
Classifier: Programming Language :: Python :: 3.14
Provides-Extra: all
Provides-Extra: docs
Provides-Extra: gmail
Provides-Extra: ldap
Provides-Extra: mssql
Provides-Extra: mysql
Provides-Extra: postgresql
Provides-Extra: saml
Provides-Extra: sso
Requires-Dist: Django (>=5.1,<7.0)
Requires-Dist: celery (>=5.3)
Requires-Dist: crispy-bootstrap5 (>=2.0)
Requires-Dist: django-auth-ldap (>=4.0) ; extra == "ldap" or extra == "all"
Requires-Dist: django-crispy-forms (>=2.0)
Requires-Dist: google-api-python-client (>=2.100) ; extra == "gmail" or extra == "all"
Requires-Dist: google-auth (>=2.20) ; extra == "gmail" or extra == "all"
Requires-Dist: mssql-django (>=1.3) ; extra == "mssql" or extra == "all"
Requires-Dist: mysqlclient (>=2.2) ; extra == "mysql" or extra == "all"
Requires-Dist: psycopg2-binary (>=2.9) ; extra == "postgresql" or extra == "all"
Requires-Dist: pyodbc (>=5.0) ; extra == "mssql" or extra == "all"
Requires-Dist: python-decouple (>=3.8)
Requires-Dist: python-ldap (>=3.4) ; extra == "ldap" or extra == "all"
Requires-Dist: python3-saml (>=1.16) ; extra == "sso" or extra == "saml" or extra == "all"
Requires-Dist: requests (>=2.31)
Requires-Dist: social-auth-app-django (>=5.4) ; extra == "sso" or extra == "all"
Requires-Dist: sphinx (>=7.0) ; extra == "docs"
Requires-Dist: sphinx-autodoc-typehints (>=1.25) ; extra == "docs"
Requires-Dist: sphinx-rtd-theme (>=2.0) ; extra == "docs"
Project-URL: Documentation, https://django-forms-workflows.readthedocs.io/
Project-URL: Homepage, https://github.com/opensensor/django-forms-workflows
Project-URL: Repository, https://github.com/opensensor/django-forms-workflows
